[
    {
        "level": "10",
        "title": "ひつぎとふたご [7KEY/LUNATIC]",
        "lr2_bmsid": "1125",
        "md5": "79dc444b48299814462ff23a2bf3ab79",
        "url_diff": "https://web.archive.org/web/20190329105351/http://www.geocities.jp/minomusiwokokoronisoete/bmssabun.html",
        "url": "http://web.archive.org/web/20110717154114/http://placase.bms.ms/music.htm",
        "artist": "plastic feat.サキト / yuyuko",
        "comment": ""
    },
    {
        "level": "6",
        "title": "ひつぎとふたご [7KEY/AFOTHER]",
        "lr2_bmsid": "91060",
        "md5": "80584225c6e81575ff8646e94b97c169",
        "url_diff": "https://darksabun.github.io/mirror/absolute/uploader/up1672.zip",
        "url": "http://web.archive.org/web/20110717154114/http://placase.bms.ms/music.htm",
        "artist": "plastic feat.サキト / yuyuko / nemes",
        "comment": ""
    },
    {
        "level": "4",
        "title": "ひつぎとふたご ～狂気ノ宴～",
        "lr2_bmsid": "666",
        "md5": "50b6f903b6cbeb0487414003f486c7a4",
        "url": "http://web.archive.org/web/20110717154114/http://placase.bms.ms/music.htm",
        "url_diff": "http://sabunbun.yukihotaru.com/sabunokiba.html",
        "artist": "plastic feat.サキト/obj BUN×BUN",
        "comment": ""
    },
    {
        "level": "9",
        "title": "ひつぎとふたご [逝]",
        "lr2_bmsid": "180987",
        "md5": "748b1b7d1244c6b977cdbf7fb3722703",
        "url": "http://web.archive.org/web/20110717154114/http://placase.bms.ms/music.htm",
        "url_diff": "http://srdbms.otodo.net/sabun/futago_srdX.zip",
        "artist": "plastic feat.サキト / obj:sarada",
        "comment": ""
    },
    {
        "level": "10",
        "title": "Central DELAY",
        "lr2_bmsid": "76551",
        "md5": "f3b5befffd5b4bb1177ba91091e72307",
        "url": "http://manbow.nothing.sh/event/event.cgi?action=More_def&num=23&event=60",
        "url_diff": "http://hakkanbms.web.fc2.com/sabun.html",
        "artist": "P.E / SGR",
        "comment": "★★2"
    },
    {
        "level": "1",
        "title": "Central DELAY [BEGINNER]",
        "lr2_bmsid": "130323",
        "md5": "3b48a96876e3c65f9598a7ae9d95e6ba",
        "url": "http://manbow.nothing.sh/event/event.cgi?action=More_def&num=23&event=60",
        "url_diff": "http://web.archive.org/http://absolute.pv.land.to/uploader/src/up2698.zip",
        "artist": "P.E / SGR / obj:月門",
        "comment": ""
    },
    {
        "level": "1",
        "title": "aliceblue (Radio Edit) (SP EX)",
        "lr2_bmsid": "25",
        "md5": "dbe5b5890e751aefbbee6187797b6e66",
        "url": "http://web.archive.org/web/20090918191807/http://www.planetoid.biz/?page_id=8",
        "url_diff": "https://dl.dropboxusercontent.com/s/g3ig60n2oi3nc9g/airsabun.zip",
        "artist": "syatten / air",
        "comment": "normal judge"
    },
    {
        "level": "3",
        "title": "aliceblue (Radio Edit) (SP EX+)",
        "lr2_bmsid": "1223",
        "md5": "5a9eede846c0a2d13e27c86326b164f8",
        "url": "http://web.archive.org/web/20090918191807/http://www.planetoid.biz/?page_id=8",
        "url_diff": "https://dl.dropboxusercontent.com/s/g3ig60n2oi3nc9g/airsabun.zip",
        "artist": "syatten / air",
        "comment": "normal judge"
    },
    {
        "level": "6",
        "title": "aliceblue (Radio Edit) (SP EX++)",
        "lr2_bmsid": "194",
        "md5": "10e32182c81f2c4fafbe18946c75b04f",
        "url": "http://web.archive.org/web/20090918191807/http://www.planetoid.biz/?page_id=8",
        "url_diff": "https://dl.dropboxusercontent.com/s/g3ig60n2oi3nc9g/airsabun.zip",
        "artist": "syatten / air",
        "comment": "normal judge"
    },
    {
        "level": "3",
        "title": "Jade Star [alternative]",
        "lr2_bmsid": "359",
        "md5": "faac4cbd630b2a01b8da4f3f40ba89b4",
        "url": "http://web.archive.org/web/20210728184302/http://shiki2.sakura.ne.jp/",
        "url_diff": "http://dl.dropbox.com/u/31329797/sabun/jadestar_altBGA%2B.zip",
        "artist": "SHIKI/ 壱air/obj:lobsak",
        "comment": "low total, normal judge"
    },
    {
        "level": "5",
        "title": "Jade Star [Dimlight]",
        "lr2_bmsid": "298934",
        "md5": "765d908b35d56f9b2bb97d0fbd37d1ff",
        "url": "http://web.archive.org/web/20210728184302/http://shiki2.sakura.ne.jp/",
        "url_diff": "https://stellabms.xyz/upload/853",
        "artist": "SHIKI / 壱air obj: qtp13",
        "comment": "low total"
    },
    {
        "level": "4",
        "title": "Pure Ruby -JUNK7-",
        "lr2_bmsid": "49164",
        "md5": "d1877ad5dc0134b27eb0238da5721eed",
        "url": "http://web.archive.org/web/20210728184302/http://shiki2.sakura.ne.jp/",
        "url_diff": "http://srdbms.otodo.net",
        "artist": "SHIKI / obj:sok",
        "comment": "kickjacks"
    },
    {
        "level": "9",
        "title": "Pure Ruby [Another+]",
        "lr2_bmsid": "646",
        "md5": "db91d03800a7a171fe8d33300fefbe2e",
        "url": "http://web.archive.org/web/20210728184302/http://shiki2.sakura.ne.jp/",
        "url_diff": "https://dl.dropboxusercontent.com/s/g3ig60n2oi3nc9g/airsabun.zip",
        "artist": "SHIKI / air",
        "comment": "only last"
    },
    {
        "level": "8",
        "title": "Angelic Layer -Heavenly7-",
        "lr2_bmsid": "533",
        "md5": "17102eac11c4f695d5c926142aaf1b64",
        "url": "http://web.archive.org/web/20210728184302/http://shiki2.sakura.ne.jp/",
        "url_diff": "http://xki.is.land.to/bms/sabun.html",
        "artist": "SHIKI/http://d.hatena.ne.jp/xki/",
        "comment": ""
    },
    {
        "level": "4",
        "title": "Angelic Layer ～Reincarnation～",
        "lr2_bmsid": "1217",
        "md5": "a1a91080d47424493ee301726ef3aaeb",
        "url": "http://web.archive.org/web/20210728184302/http://shiki2.sakura.ne.jp/",
        "url_diff": "http://sabunbun.yukihotaru.com/sabunokiba.html",
        "artist": "SHIKI / obj BUN×BUN",
        "comment": "normal judge"
    },
    {
        "level": "1",
        "title": "Evangelize (Radio Edit) [PLANET]",
        "lr2_bmsid": "42103",
        "md5": "ba976b164c8d9e397f54191860b3622a",
        "url": "http://www.dropbox.com/sh/xrr3fvlhagzsmm2/AAC0HdK_kps6UCKtDFTCkpJea/bms/Evangelize%20(Radio%20Edit).rar?dl=0",
        "url_diff": "http://web.archive.org/http://absolute.pv.land.to/uploader/src/up0507.zip",
        "artist": "syatten + 140 obj : 霜深",
        "comment": ""
    },
    {
        "level": "6",
        "title": "Evangelize (Radio Edit) (SP ミラクル)",
        "lr2_bmsid": "28",
        "md5": "7b00be2a087de2c29f5527fc439ac157",
        "url": "http://www.dropbox.com/sh/xrr3fvlhagzsmm2/AAC0HdK_kps6UCKtDFTCkpJea/bms/Evangelize%20(Radio%20Edit).rar?dl=0",
        "url_diff": "http://onedrive.live.com/?id=CE1DD07774D515B4%21241&cid=CE1DD07774D515B4&group=0",
        "artist": "syatten + 140 : obj:JEYSON",
        "comment": "low total"
    },
    {
        "level": "10",
        "title": "Evangelize (Radio Edit) (SP FRIDAY)",
        "lr2_bmsid": "1510",
        "md5": "eb961de5b7703657a08fe2dce340e5d6",
        "url": "http://www.dropbox.com/sh/xrr3fvlhagzsmm2/AAC0HdK_kps6UCKtDFTCkpJea/bms/Evangelize%20(Radio%20Edit).rar?dl=0",
        "url_diff": "http://onedrive.live.com/?id=CE1DD07774D515B4%21241&cid=CE1DD07774D515B4&group=0",
        "artist": "syatten + 140 : obj:JEYSON",
        "comment": "low total"
    },
    {
        "level": "7",
        "title": "Evangelize (Radio Edit) [Oracle]",
        "lr2_bmsid": "329382",
        "md5": "3e4ff8c96296a73d4d61c9696eb529b2",
        "url": "http://www.dropbox.com/sh/xrr3fvlhagzsmm2/AAC0HdK_kps6UCKtDFTCkpJea/bms/Evangelize%20(Radio%20Edit).rar?dl=0",
        "url_diff": "https://stellabms.xyz/upload/3579",
        "artist": "syatten + 140 Obj: Qualle",
        "comment": "sl10"
    },
    {
        "level": "8",
        "title": "Lapis [World Extend]",
        "lr2_bmsid": "300750",
        "md5": "010d5e5f5225616215c1b365f68a604b",
        "url": "http://web.archive.org/web/20210728184302/http://shiki2.sakura.ne.jp/",
        "url_diff": "https://1drv.ms/u/s!ApwaJAUHJdpymi6V8Ih_rYoKDJAj?e=2tRG9K",
        "artist": "SHIKI obj.nozomi",
        "comment": "st8~9"
    },
    {
        "level": "2",
        "title": "Lapis [Another+]",
        "lr2_bmsid": "439",
        "md5": "5c27f600d79853e8196677b0cc637019",
        "url": "http://web.archive.org/web/20210728184302/http://shiki2.sakura.ne.jp/",
        "url_diff": "https://dl.dropboxusercontent.com/s/g3ig60n2oi3nc9g/airsabun.zip",
        "artist": "SHIKI / air",
        "comment": ""
    },
    {
        "level": "7",
        "title": "Lapis [FRIDAY]",
        "lr2_bmsid": "1311",
        "md5": "f378874acfd34e09e2c1be0a1b7fdb9b",
        "url": "http://web.archive.org/web/20210728184302/http://shiki2.sakura.ne.jp/",
        "url_diff": "http://web.archive.org/http://absolute.pv.land.to/uploader/src/up0198.rar",
        "artist": "SHIKI / obj: JEYSON",
        "comment": ""
    },
    {
        "level": "2",
        "title": "G e n g a o z o _ A",
        "lr2_bmsid": "2493",
        "md5": "8d55301a933cce2ed95ad14647ad8cb3",
        "url": "http://malie.noor.jp/",
        "url_diff": "",
        "artist": "455 / rio",
        "comment": "unknown difficulty; normal judge fast double streams feels at least st3~ ish"
    },
    {
        "level": "5",
        "title": "G e n g a o z o _ E X",
        "lr2_bmsid": "127",
        "md5": "aeb2dd0707f26b1a61f6874bfd99e804",
        "url": "http://malie.noor.jp/",
        "url_diff": "http://nekokan.dyndns.info/~lobsak/bms/repair_pack.zip",
        "artist": "455 / rio / arufis",
        "comment": "st5~6? total too low"
    },
    {
        "level": "5",
        "title": "G e n g a o z o _ A F O",
        "lr2_bmsid": "117",
        "md5": "ec83546f7399d6230807a7bc66d0ac66",
        "url": "http://malie.noor.jp/",
        "url_diff": "http://web.archive.org/http://absolute.pv.land.to/",
        "artist": "455 / rio / black train",
        "comment": "more lenient recovery than EX (the base chart of)"
    },
    {
        "level": "10",
        "title": "G e n g a o z o _ G O D",
        "lr2_bmsid": "131877",
        "md5": "5110b92d997eabc3d2322556617632ad",
        "url": "http://malie.noor.jp/",
        "url_diff": "http://web.archive.org/http://absolute.pv.land.to/",
        "artist": "455 / rio / black train",
        "comment": "not ★12"
    },
    {
        "level": "3",
        "title": "A c i - L - A",
        "lr2_bmsid": "1196",
        "md5": "8fd0614318cb81d988de5c7f613abe27",
        "url": "http://malie.noor.jp/",
        "url_diff": "",
        "artist": "裏 吉 川",
        "comment": "very lenient recovery, hard clear is st5+"
    },
    {
        "level": "4",
        "title": "A c i - L - A",
        "lr2_bmsid": "493",
        "md5": "88fa1f2205bccce696cf78bbe15f5917",
        "url": "http://malie.noor.jp/",
        "url_diff": "https://web.archive.org/web/20130608043755/http://page.freett.com:80/lobsak",
        "artist": "裏 吉 川",
        "comment": "harder ending, recovery is still very lenient"
    },
    {
        "level": "9",
        "title": "A c i - L - G O D",
        "lr2_bmsid": "354",
        "md5": "dd99972264eeab7e4cd22d9a64ccb569",
        "url": "http://malie.noor.jp/",
        "url_diff": "http://web.archive.org/http://absolute.pv.land.to/",
        "artist": "裏 吉 川 / obj: black train",
        "comment": "surprisingly easier than Gengaozo_GOD"
    },
    {
        "level": "10",
        "title": "A c i - L - An...um...",
        "lr2_bmsid": "1398",
        "md5": "87f1756867d68fad094b777fc24c1bef",
        "url": "http://malie.noor.jp/",
        "url_diff": "http://web.archive.org/web/20130909065851/http://page.freett.com/ppppxy/bmsabun.zip",
        "artist": "裏 吉 川 / obj:arufis",
        "comment": "very low total + normal judge (very random dependant)"
    },
    {
        "level": "3",
        "title": "Air ANOTHER",
        "lr2_bmsid": "21",
        "md5": "de7652bd9c80b8830265336a725f7a98",
        "url": "http://web.archive.org/web/20210728184302/http://shiki2.sakura.ne.jp/",
        "url_diff": "http://nekokan.dyndns.info/~lobsak/hokan/",
        "artist": "SHIKI / rio",
        "comment": "double stair ending ala Qualia? (with anchoring no less)"
    },
    {
        "level": "4",
        "title": "Air ANOTHER+",
        "lr2_bmsid": "455",
        "md5": "5cf55487a3cb0dce8d0a40a791955e13",
        "url": "http://web.archive.org/web/20210728184302/http://shiki2.sakura.ne.jp/",
        "url_diff": "http://web.archive.org/http://absolute.pv.land.to/",
        "artist": "SHIKI / black train",
        "comment": "opening is converted to streams, otherwise the same chart"
    },
    {
        "level": "10",
        "title": "Air -EXTREME-",
        "lr2_bmsid": "742",
        "md5": "cb32378ba605aa6439840a222f83688f",
        "url": "http://web.archive.org/web/20210728184302/http://shiki2.sakura.ne.jp/",
        "url_diff": "http://web.archive.org/http://absolute.pv.land.to/",
        "artist": "SHIKI / black train",
        "comment": "st9~10?"
    },
    {
        "level": "6",
        "title": "Air -AFOTHER-",
        "lr2_bmsid": "1411",
        "md5": "eb025ebb0c8a8ff5f39e1ebce1c2d08b",
        "url": "http://web.archive.org/web/20210728184302/http://shiki2.sakura.ne.jp/",
        "url_diff": "http://web.archive.org/http://absolute.pv.land.to/",
        "artist": "SHIKI / black train",
        "comment": "trivial with the correct random (I don't even know what is this chart supposed to be...)"
    },
    {
        "level": "6",
        "title": "Air -MANIAQ-",
        "lr2_bmsid": "1234",
        "md5": "1e69627c0ca4628b67f731bc36423875",
        "url": "http://web.archive.org/web/20210728184302/http://shiki2.sakura.ne.jp/",
        "url_diff": "http://web.archive.org/http://absolute.pv.land.to/",
        "artist": "SHIKI / black train",
        "comment": ""
    },
    {
        "level": "1",
        "title": "before... [7key/虎の穴]",
        "lr2_bmsid": "2609",
        "md5": "2fe5d85b530637ef0093c954fec91378",
        "url": "https://sound.jp/brilliantharmony/",
        "url_diff": "http://web.archive.org/http://absolute.pv.land.to/",
        "artist": "やっす～ / obj:black train",
        "comment": ""
    },
    {
        "level": "4",
        "title": "before... [7key/AFOTHER]",
        "lr2_bmsid": "459",
        "md5": "6f5191238a207f05643a84d50adcc030",
        "url": "https://sound.jp/brilliantharmony/",
        "url_diff": "http://web.archive.org/http://absolute.pv.land.to/",
        "artist": "やっす～ / obj:black train",
        "comment": ""
    },
    {
        "level": "6",
        "title": "Flesvelka [Resurrection]",
        "lr2_bmsid": "73494",
        "md5": "519cc13562c5148c271cb9b13ed8807b",
        "url": "http://manbow.nothing.sh/event/event.cgi?action=More_def&num=13&event=64",
        "url_diff": "http://yumerusabun.web.fc2.com/nue.html",
        "artist": "Grand Thaw / obj:夢瑠",
        "comment": ""
    },
    {
        "level": "6",
        "title": "蒼く爽昧な夢のようで [BlackAnother]",
        "lr2_bmsid": "286590",
        "md5": "3f055cc6d0e7b394b3952b5927235860",
        "url": "http://manbow.nothing.sh/event/event.cgi?action=More_def&num=26&event=131",
        "url_diff": "",
        "artist": "ポロロッカ",
        "comment": ""
    },
    {
        "level": "9",
        "title": "RAKUGAKI NOTE",
        "lr2_bmsid": "287108",
        "md5": "9680eaf3beed0ee172bcf772843c381e",
        "url": "http://manbow.nothing.sh/event/event.cgi?action=More_def&num=84&event=131",
        "url_diff": "",
        "artist": "kas_0120",
        "comment": "RASUGOROSHI NOTE"
    },
    {
        "level": "9",
        "title": "堕楽の園 [EXTASIM]",
        "lr2_bmsid": "222820",
        "md5": "4b347c77f74ff4880673448664d0d1ea",
        "url": "https://extrose.stoicsounds.jp/_data/bms/gmtn/%2331%20%5BILLEGAL%20GOTHIC%20SCHRANZ%5D%20%E5%A0%95%E6%A5%BD%E3%81%AE%E5%9C%92.zip",
        "url_diff": "https://mirror.lovelyrad.io/bof/src/up1051.zip",
        "artist": "witch's slave Graphic by Est / obj:0war1a VS saaa",
        "comment": ""
    },
    {
        "level": "7",
        "title": "Q [SAETHER]",
        "lr2_bmsid": "211865",
        "md5": "22e753d47b54f78e2cdd1473276f5d4b",
        "url": "http://manbow.nothing.sh/event/event.cgi?action=More_def&num=7&event=101",
        "url_diff": "http://absolute.pv.land.to/uploader/src/up5491.zip",
        "artist": "tanacoro obj:saaa",
        "comment": "Q"
    },
    {
        "level": "5",
        "title": "夢人形 -Extra dream-",
        "lr2_bmsid": "1209",
        "md5": "e31b4a50d7aa493f7746c6a17f2b3069",
        "url": "http://malie.noor.jp/",
        "url_diff": "http://web.archive.org/web/20130909065851/http://page.freett.com/ppppxy/bmsabun.zip",
        "artist": "-45 obj Kz / objectpakuri:arufis",
        "comment": "56765676567656765...."
    },
    {
        "level": "9",
        "title": "デネブ・コネクション -Despair-",
        "lr2_bmsid": "318414",
        "md5": "1388f3f994d93c25b1d550c8cf05dbbd",
        "url": "https://manbow.nothing.sh/event/event.cgi?action=More_def&num=211&event=140",
        "url_diff": "https://egosa0424.github.io/sabun/deneb_nanami.zip",
        "artist": "Abel & Kamisys mov. D_unknown & KimAutomne, obj. 七海",
        "comment": "st9.5"
    },
    {
        "level": "9",
        "title": "Regain [True End Stories]",
        "lr2_bmsid": "306234",
        "md5": "419580b963e408ab3eb4bf225ea78af5",
        "url": "https://manbow.nothing.sh/event/event.cgi?action=More_def&num=242&event=137",
        "url_diff": "https://darksabun.github.io/event/bofxvii/",
        "artist": "ProjectG obj.ProjectH",
        "comment": "st10 ending"
    },
    {
        "level": "1",
        "title": "Regain [EGO DEATH]",
        "lr2_bmsid": "303931",
        "md5": "0cbc7b980f664e7e0eb2214c965c2180",
        "url": "https://manbow.nothing.sh/event/event.cgi?action=More_def&num=242&event=137",
        "url_diff": "",
        "artist": "ProjectG obj: Scely",
        "comment": ""
    },
    {
        "level": "6",
        "title": "Fleeing Sunlight -逃げ回る太陽-",
        "lr2_bmsid": "316351",
        "md5": "cdbd5dbe2b9b239cc553b03e76dff202",
        "url": "https://manbow.nothing.sh/event/event.cgi?action=More_def&num=103&event=140",
        "url_diff": "https://egosa0424.github.io/sabun/Fleeing_Sunlight_nanami.zip",
        "artist": "おみー obj:七海",
        "comment": "Klee"
    },
    {
        "level": "2",
        "title": "Fleeing Sunlight",
        "lr2_bmsid": "314859",
        "md5": "cd6d33af495b5b69d68536187c590406",
        "url": "https://manbow.nothing.sh/event/event.cgi?action=More_def&num=103&event=140",
        "url_diff": "",
        "artist": "おみー",
        "comment": "SP Another"
    },
    {
        "level": "9",
        "title": "Black Lair [EXPERT]",
        "lr2_bmsid": "276300",
        "md5": "1abcae664a42b09d1b25dc7696b3769f",
        "url": "http://web.archive.org/web/20131206203702/http://sakuzyo.net/sakuzyo_black_lair_ogg.zip",
        "url_diff": "https://bms.hexlataia.xyz/mirror/gnqg-upload/03278.zip",
        "artist": "削除 feat. void / 浪漫映像制作倶楽部 / obj : И",
        "comment": ""
    },
    {
        "level": "2",
        "title": "Black Lair [ANOTHER]",
        "lr2_bmsid": "136171",
        "md5": "16b3656f142cfe1531e2bd5e4cd9d2c3",
        "url": "http://web.archive.org/web/20131206203702/http://sakuzyo.net/sakuzyo_black_lair_ogg.zip",
        "url_diff": "",
        "artist": "削除 feat. void / 浪漫映像制作倶楽部 / obj : xi",
        "comment": ""
    },
    {
        "level": "6",
        "title": "Black Lair [INSANE]",
        "lr2_bmsid": "135842",
        "md5": "7300591ce85f888fbefe6984dc4938c3",
        "url": "http://web.archive.org/web/20131206203702/http://sakuzyo.net/sakuzyo_black_lair_ogg.zip",
        "url_diff": "",
        "artist": "削除 feat. void / 浪漫映像制作倶楽部 / obj : xi",
        "comment": ""
    },
    {
        "level": "7",
        "title": "Chocomint Mille-feuille [73Another]",
        "lr2_bmsid": "275462",
        "md5": "a96d40601a30d25eb1d694ac7d0662e6",
        "url": "https://venue.bmssearch.net/bmsshuin2/41",
        "url_diff": "",
        "artist": "NASA",
        "comment": "Delay anmitsu"
    },
    {
        "level": "9",
        "title": "Chocomint Mille-feuille [Jammed]",
        "lr2_bmsid": "275575",
        "md5": "4c286f9ab3ef84375afd508a5f084115",
        "url": "https://venue.bmssearch.net/bmsshuin2/41",
        "url_diff": "https://bms.hexlataia.xyz/mirror/gnqg-upload/03178.zip",
        "artist": "NASA obj:rebel.",
        "comment": "Delay anmitsu"
    },
    {
        "level": "9",
        "title": "Lunatic of the Full-Moon (Lunatic7)",
        "lr2_bmsid": "81417",
        "md5": "39d2d83a18b86d0e0c44df19bae677c8",
        "url": "http://cid-ce1dd07774d515b4.office.live.com/self.aspx/.Public/Lunatic%20of%20the%20Full-Moon.rar",
        "url_diff": "",
        "artist": "sun3 obj:yozuca",
        "comment": "★★1"
    },
    {
        "level": "8",
        "title": "Speed of Light [Absolute]",
        "lr2_bmsid": "241665",
        "md5": "929bd6d076aae585c7eef257e7f8b4bc",
        "url": "https://yuinore.net/2017/02/smc-package/",
        "url_diff": "",
        "artist": "Yu^ta",
        "comment": "st8.5; free recovery"
    },
    {
        "level": "0",
        "title": "Speed of Light [Another]",
        "lr2_bmsid": "241630",
        "md5": "5ca3bf72d4a03fa8823b102762ec98e5",
        "url": "https://yuinore.net/2017/02/smc-package/",
        "url_diff": "",
        "artist": "Yu^ta",
        "comment": ""
    },
    {
        "level": "0",
        "title": "あのね、涙は。 [月と星]",
        "lr2_bmsid": "259424",
        "md5": "9dd56ca71a0561a368ee819e719fac9b",
        "url": "https://venue.bmssearch.net/3/7",
        "url_diff": "https://bms.hexlataia.xyz/mirror/gnqg-upload/01935.zip",
        "artist": "竜。 feat.結月ゆかり obj:紲星あかり",
        "comment": ""
    },
    {
        "level": "11",
        "title": "あのね、涙は。 [凛]",
        "lr2_bmsid": "259442",
        "md5": "c9f44a0d9e15f2f4f72dd99a75d0ee3b",
        "url": "https://venue.bmssearch.net/3/7",
        "url_diff": "https://bms.hexlataia.xyz/mirror/gnqg-upload/01935.zip",
        "artist": "竜。 feat.結月ゆかり obj:音ゲーマーゆかり",
        "comment": "^^"
    },
    {
        "level": "9",
        "title": "あい☆こんぷりーと [平凡な女の子の優しい譜面]",
        "lr2_bmsid": "284072",
        "md5": "e7cfa8b0c28317642de91322d1dcfebe",
        "url": "http://manbow.nothing.sh/event/event.cgi?action=More_def&num=34&event=84",
        "url_diff": "https://www.dropbox.com/s/1ounmbyz685k3cu/_aiko_MarySue_yasasii.bme?dl=1",
        "artist": "ねこみりん feat.小宮真央 Movie: 石王マサト / Obj: Mary_Sue",
        "comment": "drrrr"
    },
    {
        "level": "8",
        "title": "searoad tracks =side blue=",
        "lr2_bmsid": "284701",
        "md5": "1811a0d0f5d12b6a2c06f1bbd58232b9",
        "url": "https://web.archive.org/web/20070727155516/http://sasakure.bms.ms/bms/searoadremix2.zip",
        "url_diff": "https://bms.parksulab.xyz/sabun/7/searoadremix_7.zip",
        "artist": "sasakure.UK",
        "comment": "(Arrange+) freedive tracks ↓side blue↓"
    },
    {
        "level": "3",
        "title": "searoad tracks =side blue=",
        "lr2_bmsid": "58",
        "md5": "6322a76fcbcb7660381b1fc89e8d5f4d",
        "url": "https://web.archive.org/web/20070727155516/http://sasakure.bms.ms/bms/searoadremix2.zip",
        "url_diff": "",
        "artist": "sasakure.UK",
        "comment": "(AquAStorm)"
    },
    {
        "level": "0",
        "title": "searoad tracks =side blue= [Middle Blue]",
        "lr2_bmsid": "330144",
        "md5": "450d9bc437f48a65642fa629cd3e2789",
        "url": "https://web.archive.org/web/20070727155516/http://sasakure.bms.ms/bms/searoadremix2.zip",
        "url_diff": "https://darksabun.github.io/event/1998to2024/",
        "artist": "sasakure.UK obj. HJY",
        "comment": ""
    },
    {
        "level": "8",
        "title": "ハートマークとエンドロール [Coeur]",
        "lr2_bmsid": "236253",
        "md5": "ed2ed05899fc1cddc0f3c45a030da778",
        "url": "https://www.dropbox.com/s/q42c7lcoj5mmxbx/haert_and_end.zip?dl=0",
        "url_diff": "",
        "artist": "KA-KU feat.春歌ナナ",
        "comment": "st8~9"
    },
    {
        "level": "3",
        "title": "ハートマークとエンドロール [Another+]",
        "lr2_bmsid": "234607",
        "md5": "bee8af252f715932adf387d0b0b07f85",
        "url": "https://www.dropbox.com/s/q42c7lcoj5mmxbx/haert_and_end.zip?dl=0",
        "url_diff": "",
        "artist": "KA-KU feat.春歌ナナ",
        "comment": ""
    },
    {
        "level": "10",
        "title": "D3C3MB3R [G0D]",
        "lr2_bmsid": "297553",
        "md5": "e4d3f2907ce7b35a3f9736db024756b8",
        "url": "http://manbow.nothing.sh/event/event.cgi?action=More_def&num=405&event=133",
        "url_diff": "https://stellabms.xyz/upload/742",
        "artist": "eicateve movie:龍花 / object:Restia",
        "comment": ""
    },
    {
        "level": "5",
        "title": "eve solstice mix -kuso-",
        "lr2_bmsid": "1682",
        "md5": "799baceaff9186227b4e8a8121d14eb0",
        "url": "http://1drv.ms/1AICGpH",
        "url_diff": "https://dl.dropboxusercontent.com/s/g3ig60n2oi3nc9g/airsabun.zip",
        "artist": "eir / orig: Soushi Mizutani / air",
        "comment": "TOTAL 200"
    },
    {
        "level": "2",
        "title": "evondo (sondolstice mix)",
        "lr2_bmsid": "283125",
        "md5": "9b26a2c178a5fb10c8224e45c976b7a6",
        "url": "http://1drv.ms/1AICGpH",
        "url_diff": "https://1drv.ms/u/s!AvnW9UAQwnyAkUAHyA0b1_a6Z-00?e=IyCzeD",
        "artist": "eir / orig: Soushi Mizutani / obj:Holy",
        "comment": ""
    },
    {
        "level": "9",
        "title": "Clockwork (Black Another)",
        "lr2_bmsid": "156930",
        "md5": "1146b18b7623c60e8e7dda4fbac1568d",
        "url": "https://mega.nz/folder/FNFDCQaT#wfv-iI4UuSIaGpP0oFZdtQ/file/tNtHhSRb",
        "url_diff": "",
        "artist": "MSI",
        "comment": "★★1"
    },
    {
        "level": "8",
        "title": "Betelgeuse -orion7-",
        "lr2_bmsid": "41319",
        "md5": "bd5d6333cf0fa6c86d1274ccc25a89d8",
        "url": "https://mega.nz/folder/FNFDCQaT#wfv-iI4UuSIaGpP0oFZdtQ/file/xB1QjKIS",
        "url_diff": "",
        "artist": "きのこ～ず(G.G with Anne-Ninne)",
        "comment": ""
    },
    {
        "level": "7",
        "title": "zodiac -Extra-",
        "lr2_bmsid": "1764",
        "md5": "6d7eb2859755cc31f5295296e36e024c",
        "url": "http://skydrive.live.com/?cid=fc95a680740ca8c9&id=FC95A680740CA8C9%21111",
        "url_diff": "http://web.archive.org/web/20070109011551/http://page.freett.com/mattun1130/zodiac-EX-.zip",
        "artist": "G.G obj:mattun",
        "comment": ""
    },
    {
        "level": "9",
        "title": "音弾超人ゴリライザー [ステライザー]",
        "lr2_bmsid": "300669",
        "md5": "0e1e496945f9f1b7b55f46cff48686aa",
        "url": "http://manbow.nothing.sh/event/event.cgi?action=More_def&num=82&event=104",
        "url_diff": "https://www.dropbox.com/s/3jaz8xxvfvu10eo/hero_nanami.zip?dl=1",
        "artist": "ゴリライザー制作委員会 obj:七海",
        "comment": ""
    },
    {
        "level": "3",
        "title": "音弾超人ゴリライザー [サトライザー]",
        "lr2_bmsid": "300631",
        "md5": "22b1a578c70b9d2668e18c31aaba53e4",
        "url": "http://manbow.nothing.sh/event/event.cgi?action=More_def&num=82&event=104",
        "url_diff": "https://www.dropbox.com/s/3jaz8xxvfvu10eo/hero_nanami.zip?dl=1",
        "artist": "ゴリライザー制作委員会 obj:七海",
        "comment": ""
    },
    {
        "level": "8",
        "title": "squartatrice (SP SAYATHER)",
        "lr2_bmsid": "112213",
        "md5": "2cb7ca662fa47655ac21421ed7b8aea3",
        "url": "https://extrose.stoicsounds.jp/_data/bms/gmtn/%2319%20%5BHARD%20RENAISSAYAKA%5D%20squartatrice.zip",
        "url_diff": "",
        "artist": "美樹さやか vs. 美樹さやか (fw. 美樹さやか) BGA ： 美樹さやか",
        "comment": "diavolo"
    },
    {
        "level": "6",
        "title": "The Formula [Rea'du]",
        "lr2_bmsid": "171066",
        "md5": "3b3ffc9ece8671973cea9d90f93c2e8f",
        "url": "https://dropbox.bms.ms/u/93651732/bms/%5B無課金%5DThe%20Formula.rar",
        "url_diff": "",
        "artist": "Junk / obj:kneas BGA : YARITA",
        "comment": ""
    },
    {
        "level": "7",
        "title": "Fly Again (bms edit) [Rea'du]",
        "lr2_bmsid": "140401",
        "md5": "50d06c08b90e30bd168764d3e96ccbd9",
        "url": "https://skydrive.live.com/?cid=61d67cb6f42f52a8&id=61D67CB6F42F52A8%21109",
        "url_diff": "",
        "artist": "Junk feat.Salita obj:kneas",
        "comment": ""
    },
    {
        "level": "2",
        "title": "Evoltex [HARD]",
        "lr2_bmsid": "157238",
        "md5": "44a1c0c4c2ef9dd04e1c566d5001d08a",
        "url": "http://manbow.nothing.sh/event/event.cgi?action=More_def&num=28&event=85",
        "url_diff": "",
        "artist": "Arch movie:Roaring Flame obj:四葉深雪",
        "comment": "vibro"
    },
    {
        "level": "7",
        "title": "Evoltex [Another]",
        "lr2_bmsid": "157240",
        "md5": "f593640e59b50bf0f671deff2279faf2",
        "url": "http://manbow.nothing.sh/event/event.cgi?action=More_def&num=28&event=85",
        "url_diff": "",
        "artist": "Arch movie:Roaring Flame",
        "comment": "vibruh"
    },
    {
        "level": "4",
        "title": "SEPIA -EX色-",
        "lr2_bmsid": "185",
        "md5": "b252c955763ccc430d7b085977e72cdd",
        "url": "http://shiki2.sakura.ne.jp/",
        "url_diff": "http://web.archive.org/web/20130909065851/http://page.freett.com/ppppxy/bmsabun.zip",
        "artist": "SHIKI/-45 obj:arufis",
        "comment": "Ladders"
    },
    {
        "level": "2",
        "title": "SEPIA -虎のANOTHER-",
        "lr2_bmsid": "1400",
        "md5": "8e458bd41a1e5811b19df4fb4104f7b7",
        "url": "http://shiki2.sakura.ne.jp/",
        "url_diff": "http://web.archive.org/web/20200219070214/http://absolute.pv.land.to/bms4/sepia.rar",
        "artist": "SHIKI/-45 / black train",
        "comment": "troll ending"
    },
    {
        "level": "4",
        "title": "SEPIA -AFOTHER-",
        "lr2_bmsid": "777",
        "md5": "ecdc82b1ea1c53ddc38845206a9e703d",
        "url": "http://shiki2.sakura.ne.jp/",
        "url_diff": "http://web.archive.org/web/20200219070214/http://absolute.pv.land.to/bms4/sepia.rar",
        "artist": "SHIKI/-45 / black train",
        "comment": "even more troll ending"
    },
    {
        "level": "5",
        "title": "SEPIA -MANIAQ-",
        "lr2_bmsid": "1738",
        "md5": "d63175f66ac9233c8de25b60ed8a1b7c",
        "url": "http://shiki2.sakura.ne.jp/",
        "url_diff": "http://web.archive.org/web/20200219070214/http://absolute.pv.land.to/bms4/sepia.rar",
        "artist": "SHIKI/-45 / black train",
        "comment": "Just play this one instead"
    },
    {
        "level": "8",
        "title": "Y [F]",
        "lr2_bmsid": "198026",
        "md5": "e9fc0fbbde68bfd10f2d289751a1fc6a",
        "url": "http://manbow.nothing.sh/event/event.cgi?action=More_def&num=172&event=96",
        "url_diff": "http://fenderbms.web.fc2.com/",
        "artist": "ヲルバ＝田中・ヴァニラ obj:Fender",
        "comment": ""
    },
    {
        "level": "5",
        "title": "Bloody Malie -Ex-",
        "lr2_bmsid": "131839",
        "md5": "5fae30bee9c1eac274eb919d2c94aac0",
        "url": "http://malie.noor.jp/",
        "url_diff": "http://nekokan.dyndns.info/~lobsak/bms/repair_pack.zip",
        "artist": "-45",
        "comment": "arufis... (st5 EC, hard clear impossible?)"
    },
    {
        "level": "8",
        "title": "Booboo Bounce! [Immortal]",
        "lr2_bmsid": "292151",
        "md5": "b3172f3593b9d8685769954821d65e9a",
        "url": "http://manbow.nothing.sh/event/event.cgi?action=More_def&num=137&event=133",
        "url_diff": "https://darksabun.github.io/event/bofxvi/",
        "artist": "isocosa Illust: Dr.Exodium object:Restia",
        "comment": "st8~9"
    },
    {
        "level": "4",
        "title": "妖々跋扈 (ほやほや)",
        "lr2_bmsid": "324196",
        "md5": "317d10f938b4884335106338d4e64b59",
        "url": "http://yaritaihoudie.free.fr/bms/copy/th/bakko.zip",
        "url_diff": "https://venue.bmssearch.net/sd_gray/7",
        "artist": "ZUN 差分 BMSをしていないミーティ",
        "comment": "st4~5"
    },
    {
        "level": "1",
        "title": "Cong＊Chu＊Jelly [SP ANOTHER]",
        "lr2_bmsid": "295976",
        "md5": "a556f9145914158ab05356b482937799",
        "url": "https://venue.bmssearch.net/bmsshuin3/54",
        "url_diff": "",
        "artist": "otoshi.b × みゅい × はしたかさん",
        "comment": ""
    },
    {
        "level": "6",
        "title": "Cong＊Chu＊Jelly [strawberry flavor]",
        "lr2_bmsid": "295979",
        "md5": "b4b061a9c39188bf738d381a2e6aab34",
        "url": "https://venue.bmssearch.net/bmsshuin3/54",
        "url_diff": "",
        "artist": "otoshi.b × みゅい × はしたかさん × BAECON",
        "comment": ""
    },
    {
        "level": "3",
        "title": "イナリッチ",
        "lr2_bmsid": "303313",
        "md5": "feecb86731516c02c97c216d0669a842",
        "url": "https://manbow.nothing.sh/event/event.cgi?action=More_def&num=141&event=137",
        "url_diff": "",
        "artist": "LisicA movie : 自動車原付 / illust : Orphee / obj: Frnter",
        "comment": "(Another)"
    },
    {
        "level": "9",
        "title": "イナリッチ [MONEY]",
        "lr2_bmsid": "307228",
        "md5": "04358a9776ed6fb81fe30eaa930e6eb7",
        "url": "https://manbow.nothing.sh/event/event.cgi?action=More_def&num=141&event=137",
        "url_diff": "https://stellabms.xyz/upload/1502",
        "artist": "LisicA movie : 自動車原付 / illust : Orphee / obj: Lennon",
        "comment": ""
    },
    {
        "level": "8",
        "title": "Tribute [Black Another]",
        "lr2_bmsid": "133451",
        "md5": "4cc2c2ecc2bc384b0e8e4628c8fa208d",
        "url": "https://dropbox.bms.ms/u/84148289/tribute_ogg_.zip",
        "url_diff": "",
        "artist": "imario",
        "comment": "st8~9? normal judge"
    },
    {
        "level": "9",
        "title": "神様の恋心 [KANITHER]",
        "lr2_bmsid": "296958",
        "md5": "c2a1e4e5727f42a0222f3553f6839502",
        "url": "https://venue.bmssearch.net/bmsshuin3/57",
        "url_diff": "https://muy4.github.io/muyacharts/index.html",
        "artist": "nmk feat.一花 Illust:りーふぱい/BGA:わっふゑ/obj.かに",
        "comment": ""
    },
    {
        "level": "3",
        "title": "神様の恋心",
        "lr2_bmsid": "296040",
        "md5": "1f577fbcc3f269b7315c96f8cae0c925",
        "url": "https://venue.bmssearch.net/bmsshuin3/57",
        "url_diff": "",
        "artist": "nmk feat.一花 Illust:りーふぱい/BGA:わっふゑ",
        "comment": ""
    },
    {
        "level": "7",
        "title": "AutumnBreeze for Expert",
        "lr2_bmsid": "131873",
        "md5": "755c4087937b7223c31cd17cedfce788",
        "url": "http://www5f.biglobe.ne.jp/~careless/",
        "url_diff": "http://nekokan.dyndns.info/~lobsak/bms/repair_pack.zip",
        "artist": "nmk feat.一花 Illust:りーふぱい/BGA:わっふゑ",
        "comment": ""
    },
    {
        "level": "7",
        "title": "Awaking Beat-From the next generation- [W]",
        "lr2_bmsid": "280059",
        "md5": "fe2fbfefcdf57b56bb6aaa89d6ee11cc",
        "url": "http://manbow.nothing.sh/event/event.cgi?action=More_def&num=189&event=127",
        "url_diff": "https://bms.hexlataia.xyz/mirror/gnqg-upload/03612.zip",
        "artist": "nmk feat.橘花音 obj. w",
        "comment": ""
    },
    {
        "level": "3",
        "title": "EXILE -ANOTHER-",
        "lr2_bmsid": "78682",
        "md5": "885ba306621c6be404aa02b9ceb9de0a",
        "url": "http://malie.noor.jp/",
        "url_diff": "https://darksabun.github.io/mirror/absolute/uploader/up1339.zip",
        "artist": "-45 / obj;Nemes",
        "comment": ""
    },
    {
        "level": "7",
        "title": "EXILE -NEMESIS-",
        "lr2_bmsid": "79035",
        "md5": "42b597e0fc9d2ad51909f774275464ae",
        "url": "http://malie.noor.jp/",
        "url_diff": "https://darksabun.github.io/mirror/absolute/uploader/up1339.zip",
        "artist": "-45 / obj;Nemes",
        "comment": ""
    },
    {
        "level": "11",
        "title": "EXILE -MORTAL-",
        "lr2_bmsid": "79036",
        "md5": "5f8a3aa8d06b1f5541f398e92ab8ca4f",
        "url": "http://malie.noor.jp/",
        "url_diff": "https://darksabun.github.io/mirror/absolute/uploader/up1489.zip",
        "artist": "-45 / obj;Nemes",
        "comment": "^^"
    },
    {
        "level": "12",
        "title": "EXILE -BLACK HOLE-",
        "lr2_bmsid": "86874",
        "md5": "f2ad59e1c2718001ed7789c6fa9e134e",
        "url": "http://malie.noor.jp/",
        "url_diff": "https://darksabun.github.io/mirror/absolute/uploader/up1489.zip",
        "artist": "-45 / obj;Nemes",
        "comment": "^^ (good luck mashing)"
    },
    {
        "level": "3",
        "title": "Papyrus (Maniac)",
        "lr2_bmsid": "39641",
        "md5": "c07125de4ed7fbe7cb066cc41e50e51e",
        "url": "http://manbow.nothing.sh/event/event.cgi?action=More_def&num=193&event=60",
        "url_diff": "",
        "artist": "papyrus obj: air / Movie: 浪漫映像制作倶楽部",
        "comment": ""
    },
    {
        "level": "3",
        "title": "Blooderay Malie [D-Moderate]",
        "lr2_bmsid": "309849",
        "md5": "5c155a219081f61565892b3e9f09aaa9",
        "url": "http://malie.noor.jp/",
        "url_diff": "https://stellabms.xyz/upload/1645",
        "artist": "-45 obj: qtp13",
        "comment": ""
    },
    {
        "level": "8",
        "title": "Blooderay Malie [D-Heavy]",
        "lr2_bmsid": "309848",
        "md5": "96af0b0fd5f9e61ed5078494776a951e",
        "url": "http://malie.noor.jp/",
        "url_diff": "https://stellabms.xyz/upload/1645",
        "artist": "-45 obj: qtp13",
        "comment": ""
    },
    {
        "level": "8",
        "title": "Stray Toy's Adventure!! [HARDEST]",
        "lr2_bmsid": "269138",
        "md5": "ea6d579306a3d2c7ddb36d1922212bc0",
        "url": "http://manbow.nothing.sh/event/event.cgi?action=More_def&num=341&event=123",
        "url_diff": "http://akred.web.fc2.com/bmsfile/_StrayToysAdventure-HARDEST.bms",
        "artist": "梅干茶漬け/obj:赤い人",
        "comment": "THE DIRTY OF LOUDNESS"
    },
    {
        "level": "6",
        "title": "Reallicious [Spaghettified]",
        "lr2_bmsid": "323845",
        "md5": "8daff6c3d93ca9adb37b9d80052c58e3",
        "url": "https://9domu46i.com/yuruyuru/phase16.html",
        "url_diff": "https://venue.bmssearch.net/sd_black/12",
        "artist": "Zris obj:yui",
        "comment": "hex"
    },
    {
        "level": "9",
        "title": "bibital orbital [straying]",
        "lr2_bmsid": "324345",
        "md5": "686221db564c91b0ebd67c4b55770f1e",
        "url": "https://manbow.nothing.sh/event/event.cgi?action=More_def&num=416&event=133",
        "url_diff": "https://venue.bmssearch.net/sd_gray/17",
        "artist": "utubo obj:yui",
        "comment": "hex"
    },
    {
        "level": "9",
        "title": "Faurie [ANOTHER]",
        "lr2_bmsid": "289335",
        "md5": "7943a19230bfa5565ed6def1babe7da4",
        "url": "https://manbow.nothing.sh/event/event.cgi?action=More_def&num=64&event=132",
        "url_diff": "",
        "artist": "黒皇帝 Movie: Haight",
        "comment": ""
    },
    {
        "level": "0",
        "title": "Faurie [HYPER]",
        "lr2_bmsid": "289319",
        "md5": "3a82138a8989ca0b313f44805074bb40",
        "url": "https://manbow.nothing.sh/event/event.cgi?action=More_def&num=64&event=132",
        "url_diff": "",
        "artist": "黒皇帝 Movie: Haight",
        "comment": ""
    },
    {
        "level": "12",
        "title": "Endeavor [ごめんなさい]",
        "lr2_bmsid": "103556",
        "md5": "3095e46effd1e7b2627880d72aeaef61",
        "url": "http://onedrive.live.com/?cid=fc95a680740ca8c9&id=FC95A680740CA8C9%21274&ithint=file,zip&authkey=!AIkV4RYTe2QHyDE",
        "url_diff": "https://www.axfc.net/u/3959775&key=satori",
        "artist": "ZUN(Arr.sun3)",
        "comment": "ごめんなさい..."
    },
    {
        "level": "9",
        "title": "Hi-Fi-Story [SP EXTRA]",
        "lr2_bmsid": "292378",
        "md5": "daabea71e949e92d5718ae7ba27ca0a5",
        "url": "http://manbow.nothing.sh/event/event.cgi?action=More_def&num=279&event=133",
        "url_diff": "",
        "artist": "打打だいず mov:;3ZUTAMA obj:Yosk!",
        "comment": ""
    },
    {
        "level": "8",
        "title": "Flashdance [Crazy_Life]",
        "lr2_bmsid": "269613",
        "md5": "861fabc711061a736254b8c140285010",
        "url": "http://manbow.nothing.sh/event/event.cgi?action=More_def&num=16&event=123",
        "url_diff": "https://mega.nz/#F!hbBSkQII!8i6kzQpfZ7oeMj_xws56kA",
        "artist": "music:litmus* / bms: :Poin7less movie:directed by litmus*",
        "comment": "anmitsu rating"
    },
    {
        "level": "8",
        "title": "Flashdance [#]",
        "lr2_bmsid": "268139",
        "md5": "97bc4321bc1bc37177e40ee592637cb1",
        "url": "http://manbow.nothing.sh/event/event.cgi?action=More_def&num=16&event=123",
        "url_diff": "http://gnqg.rosx.net/upload/upload.cgi?get=02379",
        "artist": "music:litmus* / bms: :Poin7less movie:directed by litmus* / obj.#",
        "comment": ""
    },
    {
        "level": "6",
        "title": "Engine [SP Insane]",
        "lr2_bmsid": "217365",
        "md5": "5e3711f2f576f3929156c9594b87efac",
        "url": "http://manbow.nothing.sh/event/event.cgi?action=More_def&num=43&event=104",
        "url_diff": "",
        "artist": "Music : eFeL / BGA : 鑓田(Alpha complex)",
        "comment": "Maximum renda"
    },
    {
        "level": "8",
        "title": "Boxel Adventure [7-1]",
        "lr2_bmsid": "284111",
        "md5": "0767b28a8b20a792a185761bee33940d",
        "url": "http://manbow.nothing.sh/event/event.cgi?action=More_def&num=138&event=127",
        "url_diff": "https://bms.hexlataia.xyz/mirror/gnqg-upload/04156.zip",
        "artist": "7mai obj: udonfor",
        "comment": "High Total"
    },
    {
        "level": "0",
        "title": "Bird Sprite -D.K.R. mix- (虎のanother)",
        "lr2_bmsid": "79",
        "md5": "12c06f4353bb52bfe9a859d9765f9664",
        "url": "http://web.archive.org/web/20070928164748/http://bof.nothing.sh/bof2005/tsunamayochan_birdsprite_HQ.rar",
        "url_diff": "http://absolute.pv.land.to/Anotherbms.html",
        "artist": "ツナマヨちゃん / obj: black train",
        "comment": ""
    },
    {
        "level": "2",
        "title": "Bird Sprite -D.K.R. mix- (afother)",
        "lr2_bmsid": "452",
        "md5": "5fce130519a3e2ba005e5886af9a83d5",
        "url": "http://web.archive.org/web/20070928164748/http://bof.nothing.sh/bof2005/tsunamayochan_birdsprite_HQ.rar",
        "url_diff": "http://absolute.pv.land.to/Anotherbms.html",
        "artist": "ツナマヨちゃん / obj: black train",
        "comment": ""
    },
    {
        "level": "5",
        "title": "Bird Sprite -D.K.R. mix- (maniaq)",
        "lr2_bmsid": "1835",
        "md5": "1d9129225c58c52126e17ca2425f4046",
        "url": "http://web.archive.org/web/20070928164748/http://bof.nothing.sh/bof2005/tsunamayochan_birdsprite_HQ.rar",
        "url_diff": "http://absolute.pv.land.to/Anotherbms.html",
        "artist": "ツナマヨちゃん / obj: black train",
        "comment": ""
    },
    {
        "level": "10",
        "title": "Imperishable Night 2006 for D",
        "lr2_bmsid": "461",
        "md5": "c6599ae9e57756c33d031b4f622324c8",
        "url": "http://web.archive.org/web/20130427145910/http://tsubu.ath.cx/~ssry/music.htm",
        "url_diff": "http://nekokan.dyndns.info/~lobsak/hokan/hokan1.html",
        "artist": "篠螺悠那 feat. 鯛の小骨",
        "comment": "maybe st10"
    },
    {
        "level": "9",
        "title": "アナログ横丁 [ディレイ六斎市]",
        "lr2_bmsid": "283320",
        "md5": "38d22090860f2d21c184ac70dd2d8dae",
        "url": "https://dropbox.bms.ms/u/64302289/makino_anolog_yokochou.rar",
        "url_diff": "https://stellabms.xyz/upload/2102",
        "artist": "牧野 obj.Guanacoite",
        "comment": "delay confusion"
    },
    {
        "level": "6",
        "title": "CO5M1C R4ILR0AD [ON3 M0RE 3XTR4]",
        "lr2_bmsid": "235174",
        "md5": "efae90d527a71d753ea7ad2847ec2006",
        "url": "http://manbow.nothing.sh/event/event.cgi?action=More_def&num=220&event=110",
        "url_diff": "http://swamelo.web.fc2.com/_CR_extra.bms",
        "artist": "kanone / obj.swa",
        "comment": "st5~6"
    },
    {
        "level": "9",
        "title": "Defeat awaken battle ship (SP AWAKEN)",
        "lr2_bmsid": "241788",
        "md5": "c7c5bc4ea5f507bb96aa2d2518efb385",
        "url": "http://manbow.nothing.sh/event/event.cgi?action=More_def&num=1&event=112",
        "url_diff": "",
        "artist": "有賀 澪 BGA:しらたき Illust:Cleome obj:伊佐奈 瑠璃",
        "comment": "Gengaozo_GOD of the Seas"
    },
    {
        "level": "7",
        "title": "風時夏 [晴海歌]",
        "lr2_bmsid": "313879",
        "md5": "8a4355653ba3f0b5c437bf0e67761c13",
        "url": "https://venue.bmssearch.net/bmskanji2/23",
        "url_diff": "",
        "artist": "otoshi.b BGI:鈴木なるひ obj:BAECON",
        "comment": "kazeharuka"
    },
    {
        "level": "1",
        "title": "風時夏 [SP INSANE]",
        "lr2_bmsid": "313879",
        "md5": "77f6d0521caf22ddc807d28ce09e0997",
        "url": "https://venue.bmssearch.net/bmskanji2/23",
        "url_diff": "",
        "artist": "otoshi.b BGI:鈴木なるひ",
        "comment": ""
    },
    {
        "level": "4",
        "title": "2038 (INSANE7)",
        "lr2_bmsid": "131698",
        "md5": "2b303ae3770d634427283093788340ec",
        "url": "http://www.yamajet.com/music/list.html",
        "url_diff": "http://slash24th.web.fc2.com/nanidosp.htm",
        "artist": "Yamajet / 壱air@Visualizer / obj:slash",
        "comment": ""
    },
    {
        "level": "6",
        "title": "サンバランド [MANIAQ]",
        "lr2_bmsid": "130307",
        "md5": "16f9bce8ee02a9ba6ccf0b2918c2d876",
        "url": "http://colosseo.nekokan.dyndns.info/c02_shuffle/detail.php?n=61",
        "url_diff": "http://slash24th.web.fc2.com/nanidosp.htm",
        "artist": "SAMBA MASTER 佐藤 -SATOH- / obj:slash",
        "comment": ""
    },
    {
        "level": "7",
        "title": "Tuk Tuk Boshi [7keys Crescent]",
        "lr2_bmsid": "86494",
        "md5": "683340fac1d376bea11c0848531ed6dd",
        "url": "https://mega.nz/folder/FNFDCQaT#wfv-iI4UuSIaGpP0oFZdtQ/file/IMtWiAob",
        "url_diff": "http://cieu.web.fc2.com/",
        "artist": "Shaman Cure-All / obj : cieu",
        "comment": "anmitsu the denims"
    },
    {
        "level": "5",
        "title": "白き星姫-Принцесса белая звезда- [декабристов]",
        "lr2_bmsid": "218012",
        "md5": "cbd93fbc5c7272714e90bb46f82ee575",
        "url": "http://manbow.nothing.sh/event/event.cgi?action=More_def&num=129&event=104",
        "url_diff": "http://absolute.pv.land.to/uploader/src/up5830.zip",
        "artist": "おみー / obj:椎葉紬",
        "comment": "st4~5"
    },
    {
        "level": "0",
        "title": "A D D i c T i O N 4 5 0 0 0 0 0 (H)",
        "lr2_bmsid": "250774",
        "md5": "bbf3cfac7d04be5f9632c8eb439989a8",
        "url": "http://manbow.nothing.sh/event/event.cgi?action=More_def&num=121&event=116",
        "url_diff": "",
        "artist": "- 4 5",
        "comment": ""
    },
    {
        "level": "3",
        "title": "A D D i c T i O N 4 5 0 0 0 0 0 (A)",
        "lr2_bmsid": "250725",
        "md5": "98da8541159bc70883dffa8d882722fc",
        "url": "http://manbow.nothing.sh/event/event.cgi?action=More_def&num=121&event=116",
        "url_diff": "",
        "artist": "- 4 5",
        "comment": ""
    },
    {
        "level": "10",
        "title": "A D D i c T i O N 4 5 0 0 0 0 0 -L u N A-",
        "lr2_bmsid": "254055",
        "md5": "2f8beb8e0b2472121ec9c5f774f8fcef",
        "url": "http://manbow.nothing.sh/event/event.cgi?action=More_def&num=121&event=116",
        "url_diff": "https://bms.hexlataia.xyz/mirror/gnqg-upload/01162.zip",
        "artist": "- 4 5 / s e l e n e .",
        "comment": "GengaoGOD_4500000"
    },
    {
        "level": "4",
        "title": "Battle TechniX [INSANE]",
        "lr2_bmsid": "304517",
        "md5": "586d33edf48aee832c835a20921f7ab1",
        "url": "https://manbow.nothing.sh/event/event.cgi?action=More_def&num=395&event=137",
        "url_diff": "",
        "artist": "38k",
        "comment": "Gaming"
    },
    {
        "level": "1",
        "title": "SunnyShinyRing -Another-",
        "lr2_bmsid": "13",
        "md5": "621ad2a006a4d39a57749c5f8dcc11b6",
        "url": "http://necoco.2-d.jp/",
        "url_diff": "",
        "artist": "みここ ＆ 虹野ひかり",
        "comment": "Back forth stairs"
    },
    {
        "level": "1",
        "title": "duty",
        "lr2_bmsid": "1831",
        "md5": "d063d3666b36cc14b176cd4438487dee",
        "url": "http://uploader.bms.ms/data/duty_mqwav.zip",
        "url_diff": "",
        "artist": "Hate BGA : S.P.S.B.",
        "comment": "★1"
    },
    {
        "level": "0",
        "title": "Scorpion Dance [INSANE]",
        "lr2_bmsid": "196718",
        "md5": "92534ba8547ae6943dc5a99b7ddd0728",
        "url": "http://manbow.nothing.sh/event/event.cgi?action=More_def&num=15&event=96",
        "url_diff": "",
        "artist": "litmus*/obj_jakko mov : litmus* & L.Ferdinant",
        "comment": ""
    },
    {
        "level": "1",
        "title": "sensitive (虎のANOTHER)",
        "lr2_bmsid": "131851",
        "md5": "8f5c7c585c944c9b98e0baad01e98519",
        "url": "http://web.archive.org/web/20070218160503/http://sazanka.sakura.ne.jp/~2tdm/bms.htm",
        "url_diff": "http://nekokan.dyndns.info/~lobsak/bms/repair_pack.zip",
        "artist": "white crystal / black train",
        "comment": ""
    },
    {
        "level": "3",
        "title": "sensitive (AFOTHER)",
        "lr2_bmsid": "131859",
        "md5": "78459a4cb7bcbece4722c835621e1bdf",
        "url": "http://web.archive.org/web/20070218160503/http://sazanka.sakura.ne.jp/~2tdm/bms.htm",
        "url_diff": "http://nekokan.dyndns.info/~lobsak/bms/repair_pack.zip",
        "artist": "white crystal / black train",
        "comment": ""
    },
    {
        "level": "6",
        "title": "sensitive (MANIAQ)",
        "lr2_bmsid": "131880",
        "md5": "5ebddb1371e925549a343ea4d4bf3e30",
        "url": "http://web.archive.org/web/20070218160503/http://sazanka.sakura.ne.jp/~2tdm/bms.htm",
        "url_diff": "http://nekokan.dyndns.info/~lobsak/bms/repair_pack.zip",
        "artist": "white crystal / black train",
        "comment": ""
    },
    {
        "level": "8",
        "title": "sensitive -GOD-",
        "lr2_bmsid": "250233",
        "md5": "dcf1fce006eae6ec81bf14a31ae1d57f",
        "url": "http://web.archive.org/web/20070218160503/http://sazanka.sakura.ne.jp/~2tdm/bms.htm",
        "url_diff": "http://gnqg.rosx.net/upload/upload.cgi?get=00968",
        "artist": "white crystal / selene.",
        "comment": ""
    },
    {
        "level": "8",
        "title": "cold planet -Blue Marble-",
        "lr2_bmsid": "70916",
        "md5": "18a3d4f7f8b1d35277e759e5643a4757",
        "url": "http://web.archive.org/web/20071210121539/http://www.geocities.jp/panda_bms/sengoku.html",
        "url_diff": "http://drowsy.hannnari.com/",
        "artist": "knot / obj:あーさん",
        "comment": "everybody dance!"
    },
    {
        "level": "7",
        "title": "Ms.Naive Princess [RAFFLESIA]",
        "lr2_bmsid": "73053",
        "md5": "1f5cf9788ce30603c5ffe261f55d6c3d",
        "url": "http://wayback.archive.org/web/20140803145510/http://roaraddiction.mods.jp/bms/x006_mnp_ogg.rar",
        "url_diff": "",
        "artist": "xenothium obj.kei",
        "comment": "there's love in the air"
    },
    {
        "level": "7",
        "title": "HAELEQUIN",
        "lr2_bmsid": "140320",
        "md5": "3c9e6197ca0dbf5bba3cd1b83603643d",
        "url": "http://manbow.nothing.sh/event/event.cgi?action=More_def&num=389&event=83",
        "url_diff": "",
        "artist": "orangentle / deadblue238",
        "comment": "YOU ARE PAIN. MY PAIN."
    },
    {
        "level": "11",
        "title": "HAELEQUIN [monather]",
        "lr2_bmsid": "183925",
        "md5": "cf7b23d82b7464c4e9aec5cf94838e86",
        "url": "http://manbow.nothing.sh/event/event.cgi?action=More_def&num=389&event=83",
        "url_diff": "https://dl.dropbox.com/s/4fvfdoycv4vmgv4/bb_HAELEQUIN_1st.bme",
        "artist": "orangentle / deadblue238 [note:MEES_]",
        "comment": "mash and pray with the very high total"
    },
    {
        "level": "6",
        "title": "TEN",
        "lr2_bmsid": "176160",
        "md5": "426ec16efd28bc5a1cbd6f707a6375f1",
        "url": "https://dl.dropbox.com/s/esdofbda23knp9w/TEN.zip",
        "url_diff": "https://docs.google.com/spreadsheets/u/0/d/15uOKGgv3433R8aP2Y9deh7HRaEG-PcymObTR32TIcBQ/pub?output=html",
        "artist": "2X / obj.XYZ",
        "comment": ""
    },
    {
        "level": "7",
        "title": "Lambda Driver [ANOTHER+]",
        "lr2_bmsid": "166013",
        "md5": "dbefc24c03e843b88cb1a1436b10638a",
        "url": "http://3t1a.net/bms/lambda_driver_ogg.zip",
        "url_diff": "https://www.axfc.net/u/3990030",
        "artist": "SPELL BREAK/obj_jakko HEART BREAK",
        "comment": ""
    },
    {
        "level": "8",
        "title": "水晶世界 ～Fracture～ [Insane]",
        "lr2_bmsid": "164968",
        "md5": "cf6b5130b319f148ef4fe63ca993a43b",
        "url": "http://manbow.nothing.sh/event/event.cgi?action=More_def&num=44&event=65",
        "url_diff": "https://dl.dropbox.com/s/zfjg13uhonfhhxw/_crystal-world_r_7i.lzh",
        "artist": "秋山 澪/obj_jakko Notes:平沢 憂",
        "comment": ""
    },
    {
        "level": "12",
        "title": "水晶世界 ～Fracture～ [yumether]",
        "lr2_bmsid": "80699",
        "md5": "cd24fd54b865c744428da2513643dd8d",
        "url": "http://manbow.nothing.sh/event/event.cgi?action=More_def&num=44&event=65",
        "url_diff": "http://yumerusabun.web.fc2.com/nue.html",
        "artist": "秋山 澪 / obj:夢瑠",
        "comment": ""
    },
    {
        "level": "9",
        "title": "先天性エゴサ依存症候群 [Hide]",
        "lr2_bmsid": "170454",
        "md5": "40673cc8ea628a9452f6ae9ac74d5817",
        "url": "http://manbow.nothing.sh/event/event.cgi?action=More_def&num=335&event=88",
        "url_diff": "http://hiiiii.web.fc2.com/sabun/",
        "artist": "ねこみりん feat.みゆ / obj:秘密 Illust:わんびぃ",
        "comment": ""
    },
    {
        "level": "10",
        "title": "Wizdomiot [ANOTHER]",
        "lr2_bmsid": "212024",
        "md5": "871c6aed53c5dd3ac35686d9a92af4f4",
        "url": "http://manbow.nothing.sh/event/event.cgi?action=More_def&num=76&event=102",
        "url_diff": "",
        "artist": "ZUN remixed by LeaF Movie:Optie",
        "comment": "10~11; may your anmitsu stay true"
    },
    {
        "level": "9",
        "title": "IKAROS [ODYSSEA]",
        "lr2_bmsid": "238363",
        "md5": "f96cf3af3d9356407bff483d27f4aecc",
        "url": "http://manbow.nothing.sh/event/event.cgi?action=More_def&num=2&event=110",
        "url_diff": "http://swamelo.web.fc2.com/_ikaros_slslsl.bme",
        "artist": "ETIA. feat. Jenga Movie: HDLV / obj: swa",
        "comment": ""
    },
    {
        "level": "8",
        "title": "幸なる旋律-the solitary melody- -福音-",
        "lr2_bmsid": "79090",
        "md5": "440e9ecc35dae241a12310b3c478eba5",
        "url": "https://web.archive.org/web/20140212164655/http://gmtn.sub.jp/carage_solitary_melody_remix.zip",
        "url_diff": "http://drowsy.hannnari.com/",
        "artist": "xenothium remixed by gmtn. obj:あーさん",
        "comment": ""
    },
    {
        "level": "8",
        "title": "Quickening 2 the RED -Sephirothic-",
        "lr2_bmsid": "95567",
        "md5": "05eda314989c59f315fe8f2ff2d6c7e9",
        "url": "http://manbow.nothing.sh/event/event.cgi?action=More_def&num=268&event=65",
        "url_diff": "http://drowsy.hannnari.com/",
        "artist": "Loki-mitsu + Mentalstock あ",
        "comment": ""
    },
    {
        "level": "10",
        "title": "TYR [Quartet]",
        "lr2_bmsid": "184380",
        "md5": "94c095ab3e44cf6ce8525dbf87c0a710",
        "url": "http://k-bms.com/party_pabat/party2014.jsp?board_num=11&num=49&order=reg&odtype=a",
        "url_diff": "https://dl.dropbox.com/s/pnpebxyv2sgan3c/PABAT%202014%20Season%20Append%20Package.zip",
        "artist": "Rune Caster / obj.swa BGA : orto",
        "comment": "check BMS Library for link"
    },
    {
        "level": "9",
        "title": "Planisphere [ANOTHER+]",
        "lr2_bmsid": "238448",
        "md5": "2a45cbc3033ad88509070c8fb036b7ec",
        "url": "http://yuinore.net/2016/11/bms-present-day1/",
        "url_diff": "",
        "artist": "Yu^ta",
        "comment": ""
    },
    {
        "level": "10",
        "title": "Inherited World [INSANE]",
        "lr2_bmsid": "217459",
        "md5": "a4b59ca055a856b9a200ccfd1bf5c7bc",
        "url": "http://manbow.nothing.sh/event/event.cgi?action=More_def&num=46&event=104",
        "url_diff": "",
        "artist": "sak Movie:猫太郎 / obj:BAECON",
        "comment": ""
    },
    {
        "level": "5",
        "title": "ShootingStar",
        "lr2_bmsid": "140543",
        "md5": "b9652852b54b4a33a8591afdee111f6b",
        "url": "http://manbow.nothing.sh/event/event.cgi?action=More_def&num=368&event=83",
        "url_diff": "",
        "artist": "Yu^ta",
        "comment": "[ANOTHER]"
    },
    {
        "level": "3",
        "title": "Ms. Steam [Another]",
        "lr2_bmsid": "303296",
        "md5": "325836401cc255f8b521e2b24516a2f1",
        "url": "https://manbow.nothing.sh/event/event.cgi?action=More_def&num=59&event=137",
        "url_diff": "",
        "artist": "MoVIIkA Movie: NaO_AnD",
        "comment": "High total meets scratch walls"
    },
    {
        "level": "8",
        "title": "Ms. Steam [Elementary My Dear]",
        "lr2_bmsid": "324895",
        "md5": "8be8fccdee2da27016699e541ee11cd3",
        "url": "https://manbow.nothing.sh/event/event.cgi?action=More_def&num=59&event=137",
        "url_diff": "https://stellabms.xyz/upload/3124",
        "artist": "MoVIIkA Movie: NaO_AnD/obj.バリツ",
        "comment": "High total meets mashing"
    },
    {
        "level": "9",
        "title": "運命論 [Atropos]",
        "lr2_bmsid": "225492",
        "md5": "b9cc5bd4194b74c2b8420a4f5c8d2ea8",
        "url": "http://manbow.nothing.sh/event/event.cgi?action=More_def&num=205&event=88",
        "url_diff": "http://lapisbms.xyz/",
        "artist": "ルゼ ☆ えみゅう。 ☆ 石王マサト obj:LAPIS",
        "comment": "a lighter ★★5-ish experience"
    },
    {
        "level": "6",
        "title": "Overjoy ★ OVERDOSE!! [Atharther]",
        "lr2_bmsid": "328057",
        "md5": "f6d87b8a9fc3e81607c9e2fff26bf163",
        "url": "https://manbow.nothing.sh/event/event.cgi?action=More_def&num=494&event=142",
        "url_diff": "https://atharnal.github.io/diff/table.html",
        "artist": "Luna Fozer obj. Atharnal / prod. BilliumMoto + 黒皇帝 + Sobrem / lyric assist. AKA / vox. vally.exe / chara. 蟹江 / illust. Shalink / mv. riguruma",
        "comment": "enough total to recover from 2% by the last 16 measures (which the rating is based on)"
    },
    {
        "level": "3",
        "title": "Whiteout",
        "lr2_bmsid": "217387",
        "md5": "e845df5c6c38add3daf627b35b76a11c",
        "url": "http://manbow.nothing.sh/event/event.cgi?action=More_def&num=13&event=104",
        "url_diff": "",
        "artist": "Re:gats& / BGA:5argon",
        "comment": "(BlackAnother)"
    },
    {
        "level": "8",
        "title": "Whiteout [&]",
        "lr2_bmsid": "217396",
        "md5": "5ee2810a0e818128c41b9385f09deb64",
        "url": "http://manbow.nothing.sh/event/event.cgi?action=More_def&num=13&event=104",
        "url_diff": "",
        "artist": "Re:gats& / BGA:5argon",
        "comment": "whiteout r.xxx"
    },
    {
        "level": "5",
        "title": "Luv 5 Dancer [EXHAUST]",
        "lr2_bmsid": "165158",
        "md5": "2941c7e5ef09640b30fb9d3ca6293bb0",
        "url": "http://uploader.bms.ms/data/luv_5_dancer_the_dear_sexys.zip",
        "url_diff": "http://web.archive.org/web/20230212194016/http://absolute.pv.land.to/uploader/src/up3837.zip",
        "artist": "The Dear Sexys/obj.poly",
        "comment": ""
    },
    {
        "level": "4",
        "title": "Exit (another7)",
        "lr2_bmsid": "1315",
        "md5": "1da468b7747759763183cdc798bc2b2a",
        "url": "http://skydrive.live.com/?cid=fc95a680740ca8c9&id=FC95A680740CA8C9%21111",
        "url_diff": "http://www.geocities.jp/azerty1s/",
        "artist": "Transin /A-zert",
        "comment": ""
    },
    {
        "level": "6",
        "title": "Rosario -another story- (very busy)",
        "lr2_bmsid": "140288",
        "md5": "471357cb816d1649486c1959d3ee0e9d",
        "url": "https://web.archive.org/web/20130508191238/http://homepage3.nifty.com/karihamo/ys_Rosario.zip",
        "url_diff": "http://absolute.pv.land.to/uploader/src/up2960.zip",
        "artist": "SB YUNE obj:ACE",
        "comment": "st7 density, quite high total"
    },
    {
        "level": "3",
        "title": "Rosario -another story- (busy)",
        "lr2_bmsid": "150",
        "md5": "cda748c5f9c545bce00eff8673cc12ea",
        "url": "https://web.archive.org/web/20130508191238/http://homepage3.nifty.com/karihamo/ys_Rosario.zip",
        "url_diff": "http://absolute.pv.land.to/uploader/src/up0166.rar",
        "artist": "SB YUNE obj:YUJI",
        "comment": "beware of the ending"
    },
    {
        "level": "5",
        "title": "Rosario -輪廻幻想譚- (SABOTHER)",
        "lr2_bmsid": "185229",
        "md5": "62e17e79a83361523d31f0a484cd2970",
        "url": "https://web.archive.org/web/20130508191238/http://homepage3.nifty.com/karihamo/ys_Rosa.zip",
        "url_diff": "https://web.archive.org/web/20190101181258/http://sabosabun.tank.jp/sabun/rosario%20sabun.zip",
        "artist": "SB_YUNE feat. 初音ミク/さ",
        "comment": "stamina draining"
    },
    {
        "level": "8",
        "title": "Rosario -輪廻幻想譚- (EX)",
        "lr2_bmsid": "185228",
        "md5": "bc5c6de58b37834a97681dac127fc94a",
        "url": "https://web.archive.org/web/20130508191238/http://homepage3.nifty.com/karihamo/ys_Rosa.zip",
        "url_diff": "https://web.archive.org/web/20190101181258/http://sabosabun.tank.jp/sabun/rosario%20sabun.zip",
        "artist": "SB_YUNE feat. 初音ミク/さ",
        "comment": "(even more) stamina draining"
    },
    {
        "level": "9",
        "title": "Forty-Four [INSANE]",
        "lr2_bmsid": "261653",
        "md5": "98a5fc8d05858c7342d03420858b8663",
        "url": "https://dropbox.bms.ms/u/59626843/xrv_44.rar",
        "url_diff": "http://gnqg.rosx.net/upload/upload.cgi?get=01766",
        "artist": "xarva / obj:LeaF",
        "comment": "stamina + hard ending"
    },
    {
        "level": "8",
        "title": "island dream [lunatic]",
        "lr2_bmsid": "265470",
        "md5": "5a83440834244c025689dc463a08437f",
        "url": "http://manbow.nothing.sh/event/event.cgi?action=More_def&num=123&event=116",
        "url_diff": "http://gnqg.rosx.net/upload/upload.cgi?get=02246",
        "artist": "canonball mukai obj:1008",
        "comment": "island diving"
    },
    {
        "level": "1",
        "title": "island dream [maniac]",
        "lr2_bmsid": "265469",
        "md5": "45c3c25bed84bc61d06cf6ec6d03e81a",
        "url": "http://manbow.nothing.sh/event/event.cgi?action=More_def&num=123&event=116",
        "url_diff": "http://gnqg.rosx.net/upload/upload.cgi?get=02246",
        "artist": "canonball mukai obj:1008",
        "comment": ""
    },
    {
        "level": "1",
        "title": "Alitatrieb [Madness]",
        "lr2_bmsid": "283422",
        "md5": "37f5309c50a7cbc2d43243ace22c91ac",
        "url": "http://manbow.nothing.sh/event/event.cgi?action=More_def&num=57&event=121",
        "url_diff": "http://gnqg.rosx.net/upload/upload.cgi?get=04060",
        "artist": "R*uLuru / obj:C4 + monaka BGA:自動車 原付",
        "comment": ""
    },
    {
        "level": "6",
        "title": "Alitatrieb [Insanity]",
        "lr2_bmsid": "283424",
        "md5": "ceedcf9712b3018c1fd7e7bf87454139",
        "url": "http://manbow.nothing.sh/event/event.cgi?action=More_def&num=57&event=121",
        "url_diff": "http://gnqg.rosx.net/upload/upload.cgi?get=04060",
        "artist": "R*uLuru / obj:C4 + monaka BGA:自動車 原付",
        "comment": ""
    },
    {
        "level": "5",
        "title": "Alitatrieb [LUNATIC]",
        "lr2_bmsid": "262628",
        "md5": "2db772c5c934cc466030a6ceb8da1175",
        "url": "http://manbow.nothing.sh/event/event.cgi?action=More_def&num=57&event=121",
        "url_diff": "",
        "artist": "R*uLuru / BGA:自動車 原付",
        "comment": ""
    },
    {
        "level": "5",
        "title": "Amethyst Moon -Pure White Crystal-",
        "lr2_bmsid": "263904",
        "md5": "1950f0e6809f704ac5ec63969ae24f9f",
        "url": "http://starkey.ivory.ne.jp/mf/mf2/detail/view/9/",
        "url_diff": "https://ux.getuploader.com/monaka_sabun_2/download/164",
        "artist": "Rethisly BGA:るっかるか / obj:monaka",
        "comment": "slappy patterns"
    },
    {
        "level": "7",
        "title": "Amethyst Moon [SP Insane]",
        "lr2_bmsid": "264470",
        "md5": "adebe810c5a1528c04454fa88ff71a04",
        "url": "http://starkey.ivory.ne.jp/mf/mf2/detail/view/9/",
        "url_diff": "",
        "artist": "Rethisly BGA:るっかるか",
        "comment": "Refischly (no pls)"
    },
    {
        "level": "6",
        "title": "春夏秋冬少女 [All Season]",
        "lr2_bmsid": "279506",
        "md5": "0bf31b7065975f58a983142a3146da1d",
        "url": "http://manbow.nothing.sh/event/event.cgi?action=More_def&num=169&event=127",
        "url_diff": "http://gnqg.rosx.net/upload/upload.cgi?get=03518",
        "artist": "Gazan obj:monaka",
        "comment": "slappy fast patterns"
    },
    {
        "level": "1",
        "title": "End Time [another]",
        "lr2_bmsid": "709",
        "md5": "38c8e7e7b08eb872e9ab1ce04b83c07d",
        "url": "http://nekokan.dyndns.info/~lobsak/genoside/",
        "url_diff": "",
        "artist": "Cres",
        "comment": "stairway to the end"
    },
    {
        "level": "6",
        "title": "End Time -Extra-",
        "lr2_bmsid": "143343",
        "md5": "076514c9ea2f3338667b6629e482bce0",
        "url": "http://nekokan.dyndns.info/~lobsak/genoside/",
        "url_diff": "http://nekokan.dyndns.info/~lobsak/bms/repair_pack.zip",
        "artist": "Cres obj: mattun",
        "comment": "wtf...?"
    },
    {
        "level": "10",
        "title": "End Time -to the death-",
        "lr2_bmsid": "143343",
        "md5": "80faa68c6b45064cb27d5c018eabd7e5",
        "url": "http://nekokan.dyndns.info/~lobsak/genoside/",
        "url_diff": "http://absolute.pv.land.to/uploader/src/up1348.rar",
        "artist": "Cres / obj:y",
        "comment": "stairway to the death"
    },
    {
        "level": "9",
        "title": "End Time A⇒Side [Deadly End]",
        "lr2_bmsid": "271818",
        "md5": "acb066266ebc83d9dae23f1009497fe3",
        "url": "http://nekokan.dyndns.info/~lobsak/genoside/",
        "url_diff": "https://ux.getuploader.com/monaka_sabun_2/download/186",
        "artist": "Cres/*8284* obj:monaka",
        "comment": "stairway to the other side"
    },
    {
        "level": "3",
        "title": "Love & Justice [AFOTHER]",
        "lr2_bmsid": "96146",
        "md5": "7c774b8922f87de19ab72e96d996726c",
        "url": "http://manbow.nothing.sh/event/event.cgi?action=More_def&num=227&event=65",
        "url_diff": "https://web.archive.org/web/20151105190255/http://absolute.pv.land.to/Anotherbms.html",
        "artist": "フロン / ラズベリル / obj: black train",
        "comment": "st3~4; Play like delay"
    },
    {
        "level": "9",
        "title": "Love & Justice [MANIAQ]",
        "lr2_bmsid": "96149",
        "md5": "d2f8edb05e9e8dd19b4106ed68c0a668",
        "url": "http://manbow.nothing.sh/event/event.cgi?action=More_def&num=227&event=65",
        "url_diff": "https://web.archive.org/web/20151105190255/http://absolute.pv.land.to/Anotherbms.html",
        "artist": "フロン / ラズベリル / obj: black train",
        "comment": "Miss...?"
    },
    {
        "level": "2",
        "title": "疾騒！痛快！正義のアヤパカガール <<JUSTICE the AYAPAKA>>",
        "lr2_bmsid": "128973",
        "md5": "1485252111bce0fd19d01705c6d35e7d",
        "url": "http://yaruki0.sakura.ne.jp/event/ondanyugi4/impression.cgi?no=7",
        "url_diff": "",
        "artist": "ZUN(Arr.髭姫) / obj:如月結 VOCAL:しゆ LYRICS：ドラホス BGA：とみー",
        "comment": "(Another)"
    },
    {
        "level": "8",
        "title": "疾騒！痛快！正義のアヤパカガール <<JUSTICE the AYAPAKA>>",
        "lr2_bmsid": "128975",
        "md5": "f5d9b9f279ca8071b6012adf09b5c293",
        "url": "http://yaruki0.sakura.ne.jp/event/ondanyugi4/impression.cgi?no=7",
        "url_diff": "",
        "artist": "ZUN(Arr.髭姫) / obj:如月結 VOCAL:しゆ LYRICS：ドラホス BGA：とみー",
        "comment": "(BlackAnother)"
    },
    {
        "level": "3",
        "title": "◆ B a r o q u e ◆ －Reincarnation－",
        "lr2_bmsid": "34032",
        "md5": "c6eb34cad636b0ff143004f77e39f9ed",
        "url": "http://www.mediafire.com/download/a6a6g72axrnp490/%E2%97%86+B+a+r+o+q+u+e+%E2%97%86.rar",
        "url_diff": "http://sabunbun.yukihotaru.com/sabunokiba.html",
        "artist": "tarolabo / obj BUN×BUN",
        "comment": ""
    },
    {
        "level": "0",
        "title": "CHASER [Another]",
        "lr2_bmsid": "712",
        "md5": "5db25f40c92eeedb385f99b29fef3811",
        "url": "http://web.archive.org/web/20210728184302/http://shiki2.sakura.ne.jp/",
        "url_diff": "",
        "artist": "SHIKI",
        "comment": ""
    },
    {
        "level": "6",
        "title": "CHASER [EX]",
        "lr2_bmsid": "383",
        "md5": "c23778c9dce653fe104576a4942e7bfb",
        "url": "http://web.archive.org/web/20210728184302/http://shiki2.sakura.ne.jp/",
        "url_diff": "http://web.archive.org//http://absolute.pv.land.to/uploader/src/up0187.zip",
        "artist": "SHIKI",
        "comment": ""
    },
    {
        "level": "0",
        "title": "Fractal [7Another]",
        "lr2_bmsid": "291844",
        "md5": "81e59fa3a2f294c5ed0bb8750f3729bb",
        "url": "http://manbow.nothing.sh/event/event.cgi?action=More_def&num=243&event=133",
        "url_diff": "",
        "artist": "SHIKI movie:140/fth",
        "comment": ""
    },
    {
        "level": "4",
        "title": "Fractal [ZOI]",
        "lr2_bmsid": "293104",
        "md5": "f2e0faae32f4db6c89c446f2284bd522",
        "url": "http://manbow.nothing.sh/event/event.cgi?action=More_def&num=243&event=133",
        "url_diff": "http://gnqg.rosx.net/upload/upload.cgi?get=04785",
        "artist": "SHIKI movie:140/fth / obj:SUZUKAZEΛ",
        "comment": ""
    },
    {
        "level": "9",
        "title": "Fractal -Luna-",
        "lr2_bmsid": "300900",
        "md5": "e05791ba3fd7eec224897da3faa1352c",
        "url": "http://manbow.nothing.sh/event/event.cgi?action=More_def&num=243&event=133",
        "url_diff": "http://gnqg.rosx.net/upload/upload.cgi?get=05468",
        "artist": "SHIKI movie:140/fth/selene.",
        "comment": ""
    },
    {
        "level": "8",
        "title": "Implexrough -Luna-",
        "lr2_bmsid": "259058",
        "md5": "591f59636e0056fcdb7edefc52d645bc",
        "url": "http://manbow.nothing.sh/event/event.cgi?action=More_def&num=365&event=116",
        "url_diff": "http://gnqg.rosx.net/upload/upload.cgi?get=1568",
        "artist": "Silentroom × mommy × Nate / selene.",
        "comment": "st8~9"
    },
    {
        "level": "2",
        "title": "どうか私を殺して下さい (latesnow)",
        "lr2_bmsid": "307492",
        "md5": "d1b40ccb0357a83e82b3b9fe82352392",
        "url": "http://rin.s101.xrea.com/",
        "url_diff": "https://stellabms.xyz/upload/1511",
        "artist": "LUNEの右手と悠里おねぇちゃんの左脚 / obj.三月ウサギ",
        "comment": ""
    },
    {
        "level": "7",
        "title": "兎は舞い降りた [HARD]",
        "lr2_bmsid": "211640",
        "md5": "eee414d4940507fcff251d2cad606adc",
        "url": "http://manbow.nothing.sh/event/event.cgi?action=More_def&num=41&event=102",
        "url_diff": "",
        "artist": "ZUN bms:乙UИ obj:yuyuko",
        "comment": ""
    },
    {
        "level": "1",
        "title": "兎は舞い降りた [NORMAL]",
        "lr2_bmsid": "211637",
        "md5": "4a2cca84e1663b382dcea1033fbd0cf8",
        "url": "http://manbow.nothing.sh/event/event.cgi?action=More_def&num=41&event=102",
        "url_diff": "",
        "artist": "ZUN bms:乙UИ obj:yuyuko",
        "comment": ""
    },
    {
        "level": "2",
        "title": "Kouma Rave Party Night [SP EXTRA]",
        "lr2_bmsid": "211308",
        "md5": "3ed91a6dfe3417ad7d663606f7208f0d",
        "url": "http://manbow.nothing.sh/event/event.cgi?action=More_def&num=13&event=102",
        "url_diff": "",
        "artist": "dj MASTER feat. 高谷紗那",
        "comment": "BGA ver."
    },
    {
        "level": "7",
        "title": "Kouma Rave Party Night [SP U.N.KNOWN]",
        "lr2_bmsid": "211289",
        "md5": "d3fe395d4c2fcdab86740afaa058f471",
        "url": "http://manbow.nothing.sh/event/event.cgi?action=More_def&num=13&event=102",
        "url_diff": "",
        "artist": "dj MASTER feat. 高谷紗那",
        "comment": "BGA ver."
    },
    {
        "level": "1",
        "title": "perfume of reunion [Nemesis]",
        "lr2_bmsid": "312816",
        "md5": "29a5d04bb897e7d87e8a5891fcef1f97",
        "url": "https://bms-mirror.com/pkg/2018/oldskoolvsfuture/%5Bem54%5Dperfume_of_reunion.zip",
        "url_diff": "https://venue.bmssearch.net/bcel_pre/29",
        "artist": "parakeet41/2 BGA:HAINA / Obj.Triforce",
        "comment": ""
    },
    {
        "level": "5",
        "title": "perfume of reunion [old's cool]",
        "lr2_bmsid": "312801",
        "md5": "3630d0ec582727bf9cf4c2fb025ccc85",
        "url": "https://bms-mirror.com/pkg/2018/oldskoolvsfuture/%5Bem54%5Dperfume_of_reunion.zip",
        "url_diff": "https://venue.bmssearch.net/bcel_pre/35",
        "artist": "parakeet41/2 BGA:HAINA / obj.hex",
        "comment": ""
    },
    {
        "level": "0",
        "title": "Ocean Fairy -BMS Edit- (ANOTHER - Legacy Ver.)",
        "lr2_bmsid": "157065",
        "md5": "b3c42e5b08c7f0c7bae570102412a0a7",
        "url": "http://manbow.nothing.sh/event/event.cgi?action=More_def&num=7&event=85",
        "url_diff": "",
        "artist": "髭姫 BGA：FleetingLovely obj：KTBM",
        "comment": "st0~1"
    },
    {
        "level": "0",
        "title": "Ocean Fairy -BMS Edit- (ANOTHER)",
        "lr2_bmsid": "157054",
        "md5": "460ae2ddea76cf26357da52203cd9f2a",
        "url": "http://manbow.nothing.sh/event/event.cgi?action=More_def&num=7&event=85",
        "url_diff": "",
        "artist": "髭姫 BGA：FleetingLovely obj：KTBM",
        "comment": "LN ver."
    },
    {
        "level": "4",
        "title": "Ocean Fairy -BMS Edit- (BLACKANOTHER)",
        "lr2_bmsid": "157082",
        "md5": "32faeae0c5b79a5a2e5c2dab6fdc3a8a",
        "url": "http://manbow.nothing.sh/event/event.cgi?action=More_def&num=7&event=85",
        "url_diff": "",
        "artist": "髭姫 BGA：FleetingLovely obj：如月結",
        "comment": ""
    },
    {
        "level": "8",
        "title": "Ocean Fairy -BMS Edit- (ΠΟΣΕΙΔΩΝ)",
        "lr2_bmsid": "157084",
        "md5": "c5f745826cd4f4673a36229ef89cbcfc",
        "url": "http://manbow.nothing.sh/event/event.cgi?action=More_def&num=7&event=85",
        "url_diff": "",
        "artist": "髭姫 BGA：FleetingLovely obj：如月結",
        "comment": "st8 with mashing + high total, otherwise st9"
    },
    {
        "level": "4",
        "title": "The Elegant Universe [INSANE]",
        "lr2_bmsid": "157067",
        "md5": "7102a579bc4f5782242838a616026d0b",
        "url": "http://manbow.nothing.sh/event/event.cgi?action=More_def&num=6&event=85",
        "url_diff": "",
        "artist": "nmk/1B",
        "comment": "difficulty by LN"
    }
]